quiettransfer/_Exceptions.py
quiettransfer/Send.py
quiettransfer/_quiettransferposix.pypy39-pp73-x86_64-linux-gnu.so
quiettransfer/__init__.py
quiettransfer/Receive.py
quiettransfer/quiet-profiles.json
quiettransfer/Reader.py
quiettransfer/__main__.py
quiet_transfer.libs/libjansson-e481c85d.so.4.10.0
quiet_transfer.libs/libliquid-a1c37250.so.1.3.1
quiet_transfer.libs/libquiet-1a00ff46.so
quiet_transfer.libs/libfec-d890db19.so
quiet_transfer-0.2.20.dist-info/top_level.txt
quiet_transfer-0.2.20.dist-info/RECORD
quiet_transfer-0.2.20.dist-info/entry_points.txt
quiet_transfer-0.2.20.dist-info/LICENSE.md
quiet_transfer-0.2.20.dist-info/METADATA
quiet_transfer-0.2.20.dist-info/WHEEL
