Metadata-Version: 2.1
Name: quiet-transfer
Version: 0.2.20
Summary: Tool to send/receive text/binary file over audio via many modulation schemes
Author-email: Matteo Tenca <matteo.tenca@gmail.com>
License: # GNU GENERAL PUBLIC LICENSE
Project-URL: homepage, https://github.com/matteotenca/quiet-transfer
Classifier: Development Status :: 5 - Production/Stable
Classifier: Intended Audience :: Developers
Classifier: Intended Audience :: Information Technology
Classifier: Programming Language :: Python :: 3.8
Classifier: Programming Language :: Python :: 3.9
Classifier: Programming Language :: Python :: 3.10
Classifier: Programming Language :: Python :: 3.11
Classifier: Programming Language :: Python :: 3.12
Classifier: Topic :: Software Development :: Libraries :: Python Modules
Classifier: Topic :: System :: Networking
Classifier: Topic :: Communications
Classifier: License :: OSI Approved :: GNU General Public License v3 or later (GPLv3+)
Requires-Python: >=3.8
License-File: LICENSE.md
Requires-Dist: cffi>=1.12.0
Requires-Dist: sounddevice
Requires-Dist: soundfile
